githubstars.py
githubstars-0.0.6.dist-info/DESCRIPTION.rst
githubstars-0.0.6.dist-info/METADATA
githubstars-0.0.6.dist-info/RECORD
githubstars-0.0.6.dist-info/WHEEL
githubstars-0.0.6.dist-info/entry_points.txt
githubstars-0.0.6.dist-info/metadata.json
githubstars-0.0.6.dist-info/top_level.txt
