Metadata-Version: 2.0
Name: githubstars
Version: 0.0.6
Summary: List repository stars and info through Gituhb v4 GraphQL API
Home-page: https://github.com/hanksudo/githubstars
Author: Hank Wang
Author-email: drapho@gmail.com
License: MIT
Keywords: stars github graphql
Platform: UNKNOWN
Classifier: Development Status :: 2 - Pre-Alpha
Classifier: Intended Audience :: Developers
Classifier: Natural Language :: English
Classifier: License :: OSI Approved :: MIT License
Classifier: Programming Language :: Python :: 2
Classifier: Programming Language :: Python :: 2.7
Classifier: Programming Language :: Python :: 3
Classifier: Programming Language :: Python :: 3.4
Classifier: Programming Language :: Python :: 3.5
Classifier: Programming Language :: Python :: 3.6
